{
  "id": "cockpit-instruments",
  "icon": "gauge",
  "order": 2,
  "status": "available",
  "lessons": [
    { "id": "altimeter" },
    { "id": "speed-horizon" },
    { "id": "compass-heading" }
  ],
  "quiz": {
    "passScore": 4,
    "sampleSize": 5,
    "questions": [
      { "id": "q1", "correct": 0 },
      { "id": "q2", "correct": 0 },
      { "id": "q3", "correct": 0 },
      { "id": "q4", "correct": 0 },
      { "id": "q5", "correct": 0 },
      { "id": "q6", "correct": 0 },
      { "id": "q7", "correct": 0 },
      { "id": "q8", "correct": 0 },
      { "id": "q9", "correct": 0 },
      { "id": "q10", "correct": 0 },
      { "id": "q11", "correct": 0 },
      { "id": "q12", "correct": 0 },
      { "id": "q13", "correct": 0 },
      { "id": "q14", "correct": 0 },
      { "id": "q15", "correct": 0 },
      { "id": "q16", "correct": 0 }
    ]
  }
}
